Workbook

Sheet Mode d'emploi
B1: Gestion de stock : mode d'emploi
B3: À quoi sert ce tableau
B5: Vous savez à tout moment ce qu'il vous reste en stock, quels produits commander, ce que vaut votre stock, et ce que vous avez vendu et gagné ce mois-ci.
B6: Les couleurs
B8: Cases jaunes : vous les remplissez.
B9: Cases grises : elles se calculent toutes seules. N'écrivez rien dedans.
B10: Étape 1 : une seule fois, au départ (onglet Produits)
B12: 1. Pour chaque produit : un code court (ex. P001), le nom, la catégorie, l'unité (pièce, carton, kg…).
B13: 2. Le prix d'achat et le prix de vente d'une unité.
B14: 3. Le stock de départ : ce que vous comptez aujourd'hui sur vos étagères.
B15: 4. Le seuil d'alerte : en dessous de cette quantité, le produit passe en « À commander ».
B16: 5. Facultatif : le fournisseur et son téléphone. La colonne « Quantité à commander » propose de quoi remonter le stock au double du seuil d'alerte.
... B29: Astuce : le tableau marche aussi sur téléphone, dans Google Sheets ou l'application Excel.

Sheet Tableau de bord
B1: Tableau de bord du stock
B3: Devise | C3: $ | D3: Écrivez $ ou FC
B4: Mois affiché (n'importe quelle date du mois) | C4: =TODAY() -> 46306 | D4: Remplacez par une date pour voir un autre mois
B6: Le stock aujourd'hui
B7: Nombre de produits | C7: =COUNTA(Produits!$A$5:$A$204) -> 2
B8: ="Valeur du stock ("&$C$3&", prix d'achat)" -> Valeur du stock ($, prix d'achat) | C8: =SUM(Produits!$L$5:$L$204) -> 816
B9: Produits à commander | C9: =COUNTIF(Produits!$M$5:$M$204,"À commander") -> 1 | D9: La liste est dans l'onglet Produits (colonne État en orange)
B10: Produits en rupture | C10: =COUNTIF(Produits!$M$5:$M$204,"Rupture") -> 0 | D10: La liste est dans l'onglet Produits (colonne État en rouge)
B11: Le mois affiché
B12: ="Ventes ("&$C$3&")" -> Ventes ($) | C12: =SUMIFS(Mouvements!$G$5:$G$1004,Mouvements!$A$5:$A$1004,">="&DATE(YEAR($C$4),MONTH($C$4),1),Mouvements!$A$5:$A$1004,"<"&DATE(YEAR($C$4),MONTH($C$4)+1,1),Mouvements!$D$5:$D$1004,"Sortie") -> 249
B13: ="Achats de marchandise ("&$C$3&")" -> Achats de marchandise ($) | C13: =SUMIFS(Mouvements!$G$5:$G$1004,Mouvements!$A$5:$A$1004,">="&DATE(YEAR($C$4),MONTH($C$4),1),Mouvements!$A$5:$A$1004,"<"&DATE(YEAR($C$4),MONTH($C$4)+1,1),Mouvements!$D$5:$D$1004,"Entrée") -> 300
B14: ="Coût d'achat des produits vendus ("&$C$3&")" -> Coût d'achat des produits vendus ($) | C14: =SUMIFS(Mouvements!$H$5:$H$1004,Mouvements!$A$5:$A$1004,">="&DATE(YEAR($C$4),MONTH($C$4),1),Mouvements!$A$5:$A$1004,"<"&DATE(YEAR($C$4),MONTH($C$4)+1,1)) -> 204
B15: ="Marge brute ("&$C$3&")" -> Marge brute ($) | C15: =C12-C14 -> 45 | D15: Ventes moins le coût d'achat de ce qui a été vendu (hors loyer, transport, salaires)
B16: Taux de marge | C16: =IF(C12=0,"-",C15/C12) -> 0.18072289

Sheet Produits
A1: Produits
A2: Jaune = à remplir · Gris = calculé automatiquement · Supprimez les lignes EXEMPLE avant de commencer
A4: Code | B4: Produit | C4: Catégorie | D4: Unité | E4: Prix d'achat (1 unité) | F4: Prix de vente (1 unité) | G4: Stock de départ | H4: Seuil d'alerte | I4: Entrées | J4: Sorties | K4: Stock actuel | L4: Valeur du stock (prix d'achat) | M4: État | N4: Fournisseur | O4: Tél. fournisseur | P4: Quantité à commander
A5: P001 | B5: EXEMPLE - Riz 25 kg | C5: Alimentation | D5: sac | E5: 30 | F5: 36 | G5: 20 | H5: 5 | I5: =IF($A5="","",SUMIFS(Mouvements!$E$5:$E$1004,Mouvements!$B$5:$B$1004,$A5,Mouvements!$D$5:$D$1004,"Entrée")) -> 10 | J5: =IF($A5="","",SUMIFS(Mouvements!$E$5:$E$1004,Mouvements!$B$5:$B$1004,$A5,Mouvements!$D$5:$D$1004,"Sortie")) -> 4 | K5: =IF($A5="","",N($G5)+$I5-$J5) -> 26 | L5: =IF($A5="","",$K5*N($E5)) -> 780 | M5: =IF($A5="","",IF($K5<=0,"Rupture",IF($K5<=N($H5),"À commander","OK"))) -> OK | N5: EXEMPLE - Grossiste A | P5: =IF($A5="","",IF($K5<=N($H5),MAX(0,2*N($H5)-$K5),0)) -> 0
A6: P002 | B6: EXEMPLE - Huile 5 L | C6: Alimentation | D6: bidon | E6: 12 | F6: 15 | G6: 10 | H6: 4 | I6: =IF($A6="","",SUMIFS(Mouvements!$E$5:$E$1004,Mouvements!$B$5:$B$1004,$A6,Mouvements!$D$5:$D$1004,"Entrée")) -> 0 | J6: =IF($A6="","",SUMIFS(Mouvements!$E$5:$E$1004,Mouvements!$B$5:$B$1004,$A6,Mouvements!$D$5:$D$1004,"Sortie")) -> 7 | K6: =IF($A6="","",N($G6)+$I6-$J6) -> 3 | L6: =IF($A6="","",$K6*N($E6)) -> 36 | M6: =IF($A6="","",IF($K6<=0,"Rupture",IF($K6<=N($H6),"À commander","OK"))) -> À commander | N6: EXEMPLE - Grossiste B | P6: =IF($A6="","",IF($K6<=N($H6),MAX(0,2*N($H6)-$K6),0)) -> 5
I7: =IF($A7="","",SUMIFS(Mouvements!$E$5:$E$1004,Mouvements!$B$5:$B$1004,$A7,Mouvements!$D$5:$D$1004,"Entrée")) | J7: =IF($A7="","",SUMIFS(Mouvements!$E$5:$E$1004,Mouvements!$B$5:$B$1004,$A7,Mouvements!$D$5:$D$1004,"Sortie")) | K7: =IF($A7="","",N($G7)+$I7-$J7) | L7: =IF($A7="","",$K7*N($E7)) | M7: =IF($A7="","",IF($K7<=0,"Rupture",IF($K7<=N($H7),"À commander","OK"))) | P7: =IF($A7="","",IF($K7<=N($H7),MAX(0,2*N($H7)-$K7),0))
I8: =IF($A8="","",SUMIFS(Mouvements!$E$5:$E$1004,Mouvements!$B$5:$B$1004,$A8,Mouvements!$D$5:$D$1004,"Entrée")) | J8: =IF($A8="","",SUMIFS(Mouvements!$E$5:$E$1004,Mouvements!$B$5:$B$1004,$A8,Mouvements!$D$5:$D$1004,"Sortie")) | K8: =IF($A8="","",N($G8)+$I8-$J8) | L8: =IF($A8="","",$K8*N($E8)) | M8: =IF($A8="","",IF($K8<=0,"Rupture",IF($K8<=N($H8),"À commander","OK"))) | P8: =IF($A8="","",IF($K8<=N($H8),MAX(0,2*N($H8)-$K8),0))
I9: =IF($A9="","",SUMIFS(Mouvements!$E$5:$E$1004,Mouvements!$B$5:$B$1004,$A9,Mouvements!$D$5:$D$1004,"Entrée")) | J9: =IF($A9="","",SUMIFS(Mouvements!$E$5:$E$1004,Mouvements!$B$5:$B$1004,$A9,Mouvements!$D$5:$D$1004,"Sortie")) | K9: =IF($A9="","",N($G9)+$I9-$J9) | L9: =IF($A9="","",$K9*N($E9)) | M9: =IF($A9="","",IF($K9<=0,"Rupture",IF($K9<=N($H9),"À commander","OK"))) | P9: =IF($A9="","",IF($K9<=N($H9),MAX(0,2*N($H9)-$K9),0))
I10: =IF($A10="","",SUMIFS(Mouvements!$E$5:$E$1004,Mouvements!$B$5:$B$1004,$A10,Mouvements!$D$5:$D$1004,"Entrée")) | J10: =IF($A10="","",SUMIFS(Mouvements!$E$5:$E$1004,Mouvements!$B$5:$B$1004,$A10,Mouvements!$D$5:$D$1004,"Sortie")) | K10: =IF($A10="","",N($G10)+$I10-$J10) | L10: =IF($A10="","",$K10*N($E10)) | M10: =IF($A10="","",IF($K10<=0,"Rupture",IF($K10<=N($H10),"À commander","OK"))) | P10: =IF($A10="","",IF($K10<=N($H10),MAX(0,2*N($H10)-$K10),0))
I11: =IF($A11="","",SUMIFS(Mouvements!$E$5:$E$1004,Mouvements!$B$5:$B$1004,$A11,Mouvements!$D$5:$D$1004,"Entrée")) | J11: =IF($A11="","",SUMIFS(Mouvements!$E$5:$E$1004,Mouvements!$B$5:$B$1004,$A11,Mouvements!$D$5:$D$1004,"Sortie")) | K11: =IF($A11="","",N($G11)+$I11-$J11) | L11: =IF($A11="","",$K11*N($E11)) | M11: =IF($A11="","",IF($K11<=0,"Rupture",IF($K11<=N($H11),"À commander","OK"))) | P11: =IF($A11="","",IF($K11<=N($H11),MAX(0,2*N($H11)-$K11),0))
I12: =IF($A12="","",SUMIFS(Mouvements!$E$5:$E$1004,Mouvements!$B$5:$B$1004,$A12,Mouvements!$D$5:$D$1004,"Entrée")) | J12: =IF($A12="","",SUMIFS(Mouvements!$E$5:$E$1004,Mouvements!$B$5:$B$1004,$A12,Mouvements!$D$5:$D$1004,"Sortie")) | K12: =IF($A12="","",N($G12)+$I12-$J12) | L12: =IF($A12="","",$K12*N($E12)) | M12: =IF($A12="","",IF($K12<=0,"Rupture",IF($K12<=N($H12),"À commander","OK"))) | P12: =IF($A12="","",IF($K12<=N($H12),MAX(0,2*N($H12)-$K12),0))
I13: =IF($A13="","",SUMIFS(Mouvements!$E$5:$E$1004,Mouvements!$B$5:$B$1004,$A13,Mouvements!$D$5:$D$1004,"Entrée")) | J13: =IF($A13="","",SUMIFS(Mouvements!$E$5:$E$1004,Mouvements!$B$5:$B$1004,$A13,Mouvements!$D$5:$D$1004,"Sortie")) | K13: =IF($A13="","",N($G13)+$I13-$J13) | L13: =IF($A13="","",$K13*N($E13)) | M13: =IF($A13="","",IF($K13<=0,"Rupture",IF($K13<=N($H13),"À commander","OK"))) | P13: =IF($A13="","",IF($K13<=N($H13),MAX(0,2*N($H13)-$K13),0))
I14: =IF($A14="","",SUMIFS(Mouvements!$E$5:$E$1004,Mouvements!$B$5:$B$1004,$A14,Mouvements!$D$5:$D$1004,"Entrée")) | J14: =IF($A14="","",SUMIFS(Mouvements!$E$5:$E$1004,Mouvements!$B$5:$B$1004,$A14,Mouvements!$D$5:$D$1004,"Sortie")) | K14: =IF($A14="","",N($G14)+$I14-$J14) | L14: =IF($A14="","",$K14*N($E14)) | M14: =IF($A14="","",IF($K14<=0,"Rupture",IF($K14<=N($H14),"À commander","OK"))) | P14: =IF($A14="","",IF($K14<=N($H14),MAX(0,2*N($H14)-$K14),0))
I15: =IF($A15="","",SUMIFS(Mouvements!$E$5:$E$1004,Mouvements!$B$5:$B$1004,$A15,Mouvements!$D$5:$D$1004,"Entrée")) | J15: =IF($A15="","",SUMIFS(Mouvements!$E$5:$E$1004,Mouvements!$B$5:$B$1004,$A15,Mouvements!$D$5:$D$1004,"Sortie")) | K15: =IF($A15="","",N($G15)+$I15-$J15) | L15: =IF($A15="","",$K15*N($E15)) | M15: =IF($A15="","",IF($K15<=0,"Rupture",IF($K15<=N($H15),"À commander","OK"))) | P15: =IF($A15="","",IF($K15<=N($H15),MAX(0,2*N($H15)-$K15),0))
I16: =IF($A16="","",SUMIFS(Mouvements!$E$5:$E$1004,Mouvements!$B$5:$B$1004,$A16,Mouvements!$D$5:$D$1004,"Entrée")) | J16: =IF($A16="","",SUMIFS(Mouvements!$E$5:$E$1004,Mouvements!$B$5:$B$1004,$A16,Mouvements!$D$5:$D$1004,"Sortie")) | K16: =IF($A16="","",N($G16)+$I16-$J16) | L16: =IF($A16="","",$K16*N($E16)) | M16: =IF($A16="","",IF($K16<=0,"Rupture",IF($K16<=N($H16),"À commander","OK"))) | P16: =IF($A16="","",IF($K16<=N($H16),MAX(0,2*N($H16)-$K16),0))
I17: =IF($A17="","",SUMIFS(Mouvements!$E$5:$E$1004,Mouvements!$B$5:$B$1004,$A17,Mouvements!$D$5:$D$1004,"Entrée")) | J17: =IF($A17="","",SUMIFS(Mouvements!$E$5:$E$1004,Mouvements!$B$5:$B$1004,$A17,Mouvements!$D$5:$D$1004,"Sortie")) | K17: =IF($A17="","",N($G17)+$I17-$J17) | L17: =IF($A17="","",$K17*N($E17)) | M17: =IF($A17="","",IF($K17<=0,"Rupture",IF($K17<=N($H17),"À commander","OK"))) | P17: =IF($A17="","",IF($K17<=N($H17),MAX(0,2*N($H17)-$K17),0))
I18: =IF($A18="","",SUMIFS(Mouvements!$E$5:$E$1004,Mouvements!$B$5:$B$1004,$A18,Mouvements!$D$5:$D$1004,"Entrée")) | J18: =IF($A18="","",SUMIFS(Mouvements!$E$5:$E$1004,Mouvements!$B$5:$B$1004,$A18,Mouvements!$D$5:$D$1004,"Sortie")) | K18: =IF($A18="","",N($G18)+$I18-$J18) | L18: =IF($A18="","",$K18*N($E18)) | M18: =IF($A18="","",IF($K18<=0,"Rupture",IF($K18<=N($H18),"À commander","OK"))) | P18: =IF($A18="","",IF($K18<=N($H18),MAX(0,2*N($H18)-$K18),0))
... I204: =IF($A204="","",SUMIFS(Mouvements!$E$5:$E$1004,Mouvements!$B$5:$B$1004,$A204,Mouvements!$D$5:$D$1004,"Entrée")) | J204: =IF($A204="","",SUMIFS(Mouvements!$E$5:$E$1004,Mouvements!$B$5:$B$1004,$A204,Mouvements!$D$5:$D$1004,"Sortie")) | K204: =IF($A204="","",N($G204)+$I204-$J204) | L204: =IF($A204="","",$K204*N($E204)) | M204: =IF($A204="","",IF($K204<=0,"Rupture",IF($K204<=N($H204),"À commander","OK"))) | P204: =IF($A204="","",IF($K204<=N($H204),MAX(0,2*N($H204)-$K204),0))

Sheet Mouvements
A1: Mouvements de stock
A2: Une ligne par entrée (réception de marchandise) ou sortie (vente). Jaune = à remplir · Gris = automatique
A4: Date | B4: Code produit | C4: Produit | D4: Type | E4: Quantité | F4: Prix unitaire | G4: Montant | H4: Coût d'achat (pour la marge) | I4: Note (client, fournisseur…)
A5: 46306 | B5: P001 | C5: =IF($B5="","",IFERROR(INDEX(Produits!$B$5:$B$204,MATCH($B5,Produits!$A$5:$A$204,0)),"Code inconnu")) -> EXEMPLE - Riz 25 kg | D5: Entrée | E5: 10 | F5: =IF(OR($B5="",$D5=""),"",IFERROR(IF($D5="Entrée",INDEX(Produits!$E$5:$E$204,MATCH($B5,Produits!$A$5:$A$204,0)),INDEX(Produits!$F$5:$F$204,MATCH($B5,Produits!$A$5:$A$204,0))),"")) -> 30 | G5: =IF(OR($F5="",$E5=""),"",$E5*$F5) -> 300 | H5: =IF(AND($D5="Sortie",$B5<>"",$E5<>""),IFERROR($E5*INDEX(Produits!$E$5:$E$204,MATCH($B5,Produits!$A$5:$A$204,0)),""),"") | I5: EXEMPLE - livraison fournisseur
A6: 46306 | B6: P001 | C6: =IF($B6="","",IFERROR(INDEX(Produits!$B$5:$B$204,MATCH($B6,Produits!$A$5:$A$204,0)),"Code inconnu")) -> EXEMPLE - Riz 25 kg | D6: Sortie | E6: 4 | F6: =IF(OR($B6="",$D6=""),"",IFERROR(IF($D6="Entrée",INDEX(Produits!$E$5:$E$204,MATCH($B6,Produits!$A$5:$A$204,0)),INDEX(Produits!$F$5:$F$204,MATCH($B6,Produits!$A$5:$A$204,0))),"")) -> 36 | G6: =IF(OR($F6="",$E6=""),"",$E6*$F6) -> 144 | H6: =IF(AND($D6="Sortie",$B6<>"",$E6<>""),IFERROR($E6*INDEX(Produits!$E$5:$E$204,MATCH($B6,Produits!$A$5:$A$204,0)),""),"") -> 120 | I6: EXEMPLE - vente
A7: 46306 | B7: P002 | C7: =IF($B7="","",IFERROR(INDEX(Produits!$B$5:$B$204,MATCH($B7,Produits!$A$5:$A$204,0)),"Code inconnu")) -> EXEMPLE - Huile 5 L | D7: Sortie | E7: 7 | F7: =IF(OR($B7="",$D7=""),"",IFERROR(IF($D7="Entrée",INDEX(Produits!$E$5:$E$204,MATCH($B7,Produits!$A$5:$A$204,0)),INDEX(Produits!$F$5:$F$204,MATCH($B7,Produits!$A$5:$A$204,0))),"")) -> 15 | G7: =IF(OR($F7="",$E7=""),"",$E7*$F7) -> 105 | H7: =IF(AND($D7="Sortie",$B7<>"",$E7<>""),IFERROR($E7*INDEX(Produits!$E$5:$E$204,MATCH($B7,Produits!$A$5:$A$204,0)),""),"") -> 84 | I7: EXEMPLE - vente
C8: =IF($B8="","",IFERROR(INDEX(Produits!$B$5:$B$204,MATCH($B8,Produits!$A$5:$A$204,0)),"Code inconnu")) | F8: =IF(OR($B8="",$D8=""),"",IFERROR(IF($D8="Entrée",INDEX(Produits!$E$5:$E$204,MATCH($B8,Produits!$A$5:$A$204,0)),INDEX(Produits!$F$5:$F$204,MATCH($B8,Produits!$A$5:$A$204,0))),"")) | G8: =IF(OR($F8="",$E8=""),"",$E8*$F8) | H8: =IF(AND($D8="Sortie",$B8<>"",$E8<>""),IFERROR($E8*INDEX(Produits!$E$5:$E$204,MATCH($B8,Produits!$A$5:$A$204,0)),""),"")
C9: =IF($B9="","",IFERROR(INDEX(Produits!$B$5:$B$204,MATCH($B9,Produits!$A$5:$A$204,0)),"Code inconnu")) | F9: =IF(OR($B9="",$D9=""),"",IFERROR(IF($D9="Entrée",INDEX(Produits!$E$5:$E$204,MATCH($B9,Produits!$A$5:$A$204,0)),INDEX(Produits!$F$5:$F$204,MATCH($B9,Produits!$A$5:$A$204,0))),"")) | G9: =IF(OR($F9="",$E9=""),"",$E9*$F9) | H9: =IF(AND($D9="Sortie",$B9<>"",$E9<>""),IFERROR($E9*INDEX(Produits!$E$5:$E$204,MATCH($B9,Produits!$A$5:$A$204,0)),""),"")
C10: =IF($B10="","",IFERROR(INDEX(Produits!$B$5:$B$204,MATCH($B10,Produits!$A$5:$A$204,0)),"Code inconnu")) | F10: =IF(OR($B10="",$D10=""),"",IFERROR(IF($D10="Entrée",INDEX(Produits!$E$5:$E$204,MATCH($B10,Produits!$A$5:$A$204,0)),INDEX(Produits!$F$5:$F$204,MATCH($B10,Produits!$A$5:$A$204,0))),"")) | G10: =IF(OR($F10="",$E10=""),"",$E10*$F10) | H10: =IF(AND($D10="Sortie",$B10<>"",$E10<>""),IFERROR($E10*INDEX(Produits!$E$5:$E$204,MATCH($B10,Produits!$A$5:$A$204,0)),""),"")
C11: =IF($B11="","",IFERROR(INDEX(Produits!$B$5:$B$204,MATCH($B11,Produits!$A$5:$A$204,0)),"Code inconnu")) | F11: =IF(OR($B11="",$D11=""),"",IFERROR(IF($D11="Entrée",INDEX(Produits!$E$5:$E$204,MATCH($B11,Produits!$A$5:$A$204,0)),INDEX(Produits!$F$5:$F$204,MATCH($B11,Produits!$A$5:$A$204,0))),"")) | G11: =IF(OR($F11="",$E11=""),"",$E11*$F11) | H11: =IF(AND($D11="Sortie",$B11<>"",$E11<>""),IFERROR($E11*INDEX(Produits!$E$5:$E$204,MATCH($B11,Produits!$A$5:$A$204,0)),""),"")
C12: =IF($B12="","",IFERROR(INDEX(Produits!$B$5:$B$204,MATCH($B12,Produits!$A$5:$A$204,0)),"Code inconnu")) | F12: =IF(OR($B12="",$D12=""),"",IFERROR(IF($D12="Entrée",INDEX(Produits!$E$5:$E$204,MATCH($B12,Produits!$A$5:$A$204,0)),INDEX(Produits!$F$5:$F$204,MATCH($B12,Produits!$A$5:$A$204,0))),"")) | G12: =IF(OR($F12="",$E12=""),"",$E12*$F12) | H12: =IF(AND($D12="Sortie",$B12<>"",$E12<>""),IFERROR($E12*INDEX(Produits!$E$5:$E$204,MATCH($B12,Produits!$A$5:$A$204,0)),""),"")
C13: =IF($B13="","",IFERROR(INDEX(Produits!$B$5:$B$204,MATCH($B13,Produits!$A$5:$A$204,0)),"Code inconnu")) | F13: =IF(OR($B13="",$D13=""),"",IFERROR(IF($D13="Entrée",INDEX(Produits!$E$5:$E$204,MATCH($B13,Produits!$A$5:$A$204,0)),INDEX(Produits!$F$5:$F$204,MATCH($B13,Produits!$A$5:$A$204,0))),"")) | G13: =IF(OR($F13="",$E13=""),"",$E13*$F13) | H13: =IF(AND($D13="Sortie",$B13<>"",$E13<>""),IFERROR($E13*INDEX(Produits!$E$5:$E$204,MATCH($B13,Produits!$A$5:$A$204,0)),""),"")
C14: =IF($B14="","",IFERROR(INDEX(Produits!$B$5:$B$204,MATCH($B14,Produits!$A$5:$A$204,0)),"Code inconnu")) | F14: =IF(OR($B14="",$D14=""),"",IFERROR(IF($D14="Entrée",INDEX(Produits!$E$5:$E$204,MATCH($B14,Produits!$A$5:$A$204,0)),INDEX(Produits!$F$5:$F$204,MATCH($B14,Produits!$A$5:$A$204,0))),"")) | G14: =IF(OR($F14="",$E14=""),"",$E14*$F14) | H14: =IF(AND($D14="Sortie",$B14<>"",$E14<>""),IFERROR($E14*INDEX(Produits!$E$5:$E$204,MATCH($B14,Produits!$A$5:$A$204,0)),""),"")
C15: =IF($B15="","",IFERROR(INDEX(Produits!$B$5:$B$204,MATCH($B15,Produits!$A$5:$A$204,0)),"Code inconnu")) | F15: =IF(OR($B15="",$D15=""),"",IFERROR(IF($D15="Entrée",INDEX(Produits!$E$5:$E$204,MATCH($B15,Produits!$A$5:$A$204,0)),INDEX(Produits!$F$5:$F$204,MATCH($B15,Produits!$A$5:$A$204,0))),"")) | G15: =IF(OR($F15="",$E15=""),"",$E15*$F15) | H15: =IF(AND($D15="Sortie",$B15<>"",$E15<>""),IFERROR($E15*INDEX(Produits!$E$5:$E$204,MATCH($B15,Produits!$A$5:$A$204,0)),""),"")
C16: =IF($B16="","",IFERROR(INDEX(Produits!$B$5:$B$204,MATCH($B16,Produits!$A$5:$A$204,0)),"Code inconnu")) | F16: =IF(OR($B16="",$D16=""),"",IFERROR(IF($D16="Entrée",INDEX(Produits!$E$5:$E$204,MATCH($B16,Produits!$A$5:$A$204,0)),INDEX(Produits!$F$5:$F$204,MATCH($B16,Produits!$A$5:$A$204,0))),"")) | G16: =IF(OR($F16="",$E16=""),"",$E16*$F16) | H16: =IF(AND($D16="Sortie",$B16<>"",$E16<>""),IFERROR($E16*INDEX(Produits!$E$5:$E$204,MATCH($B16,Produits!$A$5:$A$204,0)),""),"")
C17: =IF($B17="","",IFERROR(INDEX(Produits!$B$5:$B$204,MATCH($B17,Produits!$A$5:$A$204,0)),"Code inconnu")) | F17: =IF(OR($B17="",$D17=""),"",IFERROR(IF($D17="Entrée",INDEX(Produits!$E$5:$E$204,MATCH($B17,Produits!$A$5:$A$204,0)),INDEX(Produits!$F$5:$F$204,MATCH($B17,Produits!$A$5:$A$204,0))),"")) | G17: =IF(OR($F17="",$E17=""),"",$E17*$F17) | H17: =IF(AND($D17="Sortie",$B17<>"",$E17<>""),IFERROR($E17*INDEX(Produits!$E$5:$E$204,MATCH($B17,Produits!$A$5:$A$204,0)),""),"")
C18: =IF($B18="","",IFERROR(INDEX(Produits!$B$5:$B$204,MATCH($B18,Produits!$A$5:$A$204,0)),"Code inconnu")) | F18: =IF(OR($B18="",$D18=""),"",IFERROR(IF($D18="Entrée",INDEX(Produits!$E$5:$E$204,MATCH($B18,Produits!$A$5:$A$204,0)),INDEX(Produits!$F$5:$F$204,MATCH($B18,Produits!$A$5:$A$204,0))),"")) | G18: =IF(OR($F18="",$E18=""),"",$E18*$F18) | H18: =IF(AND($D18="Sortie",$B18<>"",$E18<>""),IFERROR($E18*INDEX(Produits!$E$5:$E$204,MATCH($B18,Produits!$A$5:$A$204,0)),""),"")
C19: =IF($B19="","",IFERROR(INDEX(Produits!$B$5:$B$204,MATCH($B19,Produits!$A$5:$A$204,0)),"Code inconnu")) | F19: =IF(OR($B19="",$D19=""),"",IFERROR(IF($D19="Entrée",INDEX(Produits!$E$5:$E$204,MATCH($B19,Produits!$A$5:$A$204,0)),INDEX(Produits!$F$5:$F$204,MATCH($B19,Produits!$A$5:$A$204,0))),"")) | G19: =IF(OR($F19="",$E19=""),"",$E19*$F19) | H19: =IF(AND($D19="Sortie",$B19<>"",$E19<>""),IFERROR($E19*INDEX(Produits!$E$5:$E$204,MATCH($B19,Produits!$A$5:$A$204,0)),""),"")
... C1004: =IF($B1004="","",IFERROR(INDEX(Produits!$B$5:$B$204,MATCH($B1004,Produits!$A$5:$A$204,0)),"Code inconnu")) | F1004: =IF(OR($B1004="",$D1004=""),"",IFERROR(IF($D1004="Entrée",INDEX(Produits!$E$5:$E$204,MATCH($B1004,Produits!$A$5:$A$204,0)),INDEX(Produits!$F$5:$F$204,MATCH($B1004,Produits!$A$5:$A$204,0))),"")) | G1004: =IF(OR($F1004="",$E1004=""),"",$E1004*$F1004) | H1004: =IF(AND($D1004="Sortie",$B1004<>"",$E1004<>""),IFERROR($E1004*INDEX(Produits!$E$5:$E$204,MATCH($B1004,Produits!$A$5:$A$204,0)),""),"")
